peoplegraph_api_client/__init__.py
peoplegraph_api_client/client.py
peoplegraph_api_client/main.py
peoplegraph_api_client-0.1.1.dist-info/DESCRIPTION.rst
peoplegraph_api_client-0.1.1.dist-info/METADATA
peoplegraph_api_client-0.1.1.dist-info/RECORD
peoplegraph_api_client-0.1.1.dist-info/WHEEL
peoplegraph_api_client-0.1.1.dist-info/entry_points.txt
peoplegraph_api_client-0.1.1.dist-info/metadata.json
peoplegraph_api_client-0.1.1.dist-info/top_level.txt
